ALSHBG/__init__.py
ALSHBG/checkerUS.py
ALSHBG/downloadx.py
ALSHBG-0.0.6.dist-info/LICENSE
ALSHBG-0.0.6.dist-info/METADATA
ALSHBG-0.0.6.dist-info/WHEEL
ALSHBG-0.0.6.dist-info/top_level.txt
ALSHBG-0.0.6.dist-info/RECORD
